reporter/pebblo_report.py
reporter/reporter.py
nishan_cli-0.1.0.dist-info/METADATA
nishan_cli-0.1.0.dist-info/WHEEL
nishan_cli-0.1.0.dist-info/entry_points.txt
nishan_cli-0.1.0.dist-info/top_level.txt
nishan_cli-0.1.0.dist-info/RECORD
