Metadata-Version: 2.2
Name: nishan-cli
Version: 0.1.0
Summary: CLI tool for Pebblo
Author-email: Pebblo Authors <pebblo@daxa.ai>
Project-URL: Homepage, https://github.com/daxa-ai/pebblo
Project-URL: Bug-Tracker, https://github.com/daxa-ai/pebblo/issues
Project-URL: Funding, https://donate.pypi.org
Project-URL: Source, https://github.com/daxa-ai/pebblo/
Classifier: Development Status :: 3 - Alpha
Classifier: Intended Audience :: Developers
Classifier: Topic :: Software Development :: Build Tools
Classifier: Operating System :: OS Independent
Classifier: Programming Language :: Python :: 3
Classifier: Programming Language :: Python :: 3.9
Classifier: Programming Language :: Python :: 3.10
Classifier: Programming Language :: Python :: 3.11
Classifier: Programming Language :: Python :: 3.12
Requires-Python: >=3.9
Requires-Dist: requests
Requires-Dist: PyYAML==6.0.2
Requires-Dist: importlib-metadata==8.6.1
